cs/mappings.py
cs_mappings-20250915.dist-info/WHEEL
cs_mappings-20250915.dist-info/METADATA
cs_mappings-20250915.dist-info/RECORD
