Metadata-Version: 2.4
Name: cs-mappings
Version: 20250915
Summary: Facilities for mappings and objects associated with mappings.
Keywords: python2,python3
Author-email: Cameron Simpson <cs@cskk.id.au>
Requires-Python: >=3.6
Classifier: Programming Language :: Python
Classifier: Programming Language :: Python :: 3
Classifier: Development Status :: 4 - Beta
Classifier: Intended Audience :: Developers
Classifier: Operating System :: OS Independent
Classifier: Topic :: Software Development :: Libraries :: Python Modules
Classifier: License :: OSI Approved :: GNU General Public License v3 or later (GPLv3+)
Requires-Dist: cs.deco>=20250914
Requires-Dist: cs.lex>=20250914
Requires-Dist: cs.logutils>=20250323
Requires-Dist: cs.pfx>=20250914
Requires-Dist: cs.seq>=20250914
Requires-Dist: cs.sharedfile>=20211208
Project-URL: MonoRepo Commits, https://bitbucket.org/cameron_simpson/css/commits/branch/main
Project-URL: Monorepo Git Mirror, https://github.com/cameron-simpson/css
Project-URL: Monorepo Hg/Mercurial Mirror, https://hg.sr.ht/~cameron-simpson/css
Project-URL: Source, https://github.com/cameron-simpson/css/blob/main/lib/python/cs/mappings.py
